BFPI/BFPI.py
BFPI/setup.py
BFPI-4.0.1.dist-info/METADATA
BFPI-4.0.1.dist-info/WHEEL
BFPI-4.0.1.dist-info/top_level.txt
BFPI-4.0.1.dist-info/RECORD
