Metadata-Version: 2.1
Name: BFPI
Version: 4.0.1
Summary: BFPI: Exactly what it sounds like
Home-page: https://github.com/TvoozMagnificent/BrainFuckPlusInterpreter
Author: TvoozMagnificent
Author-email: luchang1106@icloud.com
License: MIT
Platform: UNKNOWN
Classifier: License :: OSI Approved :: MIT License
Classifier: Programming Language :: Python :: 3
Classifier: Programming Language :: Python :: 3.7
Requires-Dist: colorama
